stm32cli/__init__.py
stm32cli/__main__.py
stm32cli/boot.py
stm32cli/bsp.py
stm32cli/cmd.py
stm32cli/uart.py
stm32cli-0.0.12.dist-info/LICENSE
stm32cli-0.0.12.dist-info/METADATA
stm32cli-0.0.12.dist-info/WHEEL
stm32cli-0.0.12.dist-info/entry_points.txt
stm32cli-0.0.12.dist-info/top_level.txt
stm32cli-0.0.12.dist-info/RECORD
